punczh2en/__init__.py
punczh2en/punczh2en.py
punczh2en-1.0.5.dist-info/LICENSE
punczh2en-1.0.5.dist-info/METADATA
punczh2en-1.0.5.dist-info/WHEEL
punczh2en-1.0.5.dist-info/top_level.txt
punczh2en-1.0.5.dist-info/RECORD
