Metadata-Version: 2.1
Name: punczh2en
Version: 1.0.5
Summary: a punctuation tool
Home-page: UNKNOWN
Author: Malchut
Author-email: 
License: UNKNOWN
Platform: UNKNOWN
Classifier: Programming Language :: Python :: 3
Classifier: License :: OSI Approved :: MIT License
Classifier: Operating System :: OS Independent
Requires-Python: >=3.6
License-File: LICENSE
